<?xml version="1.0" encoding="UTF-8"?>
<!DOCTYPE mapper PUBLIC "-//mybatis.org//DTD Mapper 3.0//EN" "http://mybatis.org/dtd/mybatis-3-mapper.dtd">
<mapper namespace="club.bagedate.o2o.mapper.ShopCategoryMapper">
  <select id="queryShopCategory" parameterType="club.bagedate.o2o.entity.ShopCategory" resultType="club.bagedate.o2o.entity.ShopCategory">
    select * from shopcategory
    <where>
      <if test="shopCategoryCondition.shopcategoryid!=null">
        and shopCategoryParentId is null
      </if>
      <if test="shopCategoryCondition.shopcategorydesc!=null">
        and shopCategoryParentId is not null
      </if>
      <if test="shopCategoryCondition.shopcategoryparentid!=null">
        and shopCategoryParentId = #{shopCategoryCondition.shopcategoryparentid}
      </if>
    </where>
    ORDER BY
    shopCategoryPriority DESC
  </select>
  <resultMap id="BaseResultMap" type="club.bagedate.o2o.entity.ShopCategory">
    <!--
      WARNING - @mbg.generated
      This element is automatically generated by MyBatis Generator, do not modify.
      This element was generated on Tue May 14 10:48:08 CST 2019.
    -->
    <id column="shopCategoryId" jdbcType="INTEGER" property="shopcategoryid" />
    <result column="shopCategoryPriority" jdbcType="INTEGER" property="shopcategorypriority" />
    <result column="shopCategoryParentId" jdbcType="INTEGER" property="shopcategoryparentid" />
    <result column="shopCategoryName" jdbcType="VARCHAR" property="shopcategoryname" />
    <result column="shopCategoryDesc" jdbcType="VARCHAR" property="shopcategorydesc" />
    <result column="shopCategoryImg" jdbcType="VARCHAR" property="shopcategoryimg" />
    <result column="shopCategoryCreateTime" jdbcType="TIMESTAMP" property="shopcategorycreatetime" />
    <result column="shopCategoryUpdateTime" jdbcType="TIMESTAMP" property="shopcategoryupdatetime" />
  </resultMap>
  <sql id="Example_Where_Clause">
    <!--
      WARNING - @mbg.generated
      This element is automatically generated by MyBatis Generator, do not modify.
      This element was generated on Tue May 14 10:48:08 CST 2019.
    -->
    <where>
      <foreach collection="oredCriteria" item="criteria" separator="or">
        <if test="criteria.valid">
          <trim prefix="(" prefixOverrides="and" suffix=")">
            <foreach collection="criteria.criteria" item="criterion">
              <choose>
                <when test="criterion.noValue">
                  and ${criterion.condition}
                </when>
                <when test="criterion.singleValue">
                  and ${criterion.condition} #{criterion.value}
                </when>
                <when test="criterion.betweenValue">
                  and ${criterion.condition} #{criterion.value} and #{criterion.secondValue}
                </when>
                <when test="criterion.listValue">
                  and ${criterion.condition}
                  <foreach close=")" collection="criterion.value" item="listItem" open="(" separator=",">
                    #{listItem}
                  </foreach>
                </when>
              </choose>
            </foreach>
          </trim>
        </if>
      </foreach>
    </where>
  </sql>
  <sql id="Update_By_Example_Where_Clause">
    <!--
      WARNING - @mbg.generated
      This element is automatically generated by MyBatis Generator, do not modify.
      This element was generated on Tue May 14 10:48:08 CST 2019.
    -->
    <where>
      <foreach collection="example.oredCriteria" item="criteria" separator="or">
        <if test="criteria.valid">
          <trim prefix="(" prefixOverrides="and" suffix=")">
            <foreach collection="criteria.criteria" item="criterion">
              <choose>
                <when test="criterion.noValue">
                  and ${criterion.condition}
                </when>
                <when test="criterion.singleValue">
                  and ${criterion.condition} #{criterion.value}
                </when>
                <when test="criterion.betweenValue">
                  and ${criterion.condition} #{criterion.value} and #{criterion.secondValue}
                </when>
                <when test="criterion.listValue">
                  and ${criterion.condition}
                  <foreach close=")" collection="criterion.value" item="listItem" open="(" separator=",">
                    #{listItem}
                  </foreach>
                </when>
              </choose>
            </foreach>
          </trim>
        </if>
      </foreach>
    </where>
  </sql>
  <sql id="Base_Column_List">
    <!--
      WARNING - @mbg.generated
      This element is automatically generated by MyBatis Generator, do not modify.
      This element was generated on Tue May 14 10:48:08 CST 2019.
    -->
    shopCategoryId, shopCategoryPriority, shopCategoryParentId, shopCategoryName, shopCategoryDesc, 
    shopCategoryImg, shopCategoryCreateTime, shopCategoryUpdateTime
  </sql>
  <select id="selectByExample" parameterType="club.bagedate.o2o.entity.ShopCategoryExample" resultMap="BaseResultMap">
    <!--
      WARNING - @mbg.generated
      This element is automatically generated by MyBatis Generator, do not modify.
      This element was generated on Tue May 14 10:48:08 CST 2019.
    -->
    select
    <if test="distinct">
      distinct
    </if>
    <include refid="Base_Column_List" />
    from shopcategory
    <if test="_parameter != null">
      <include refid="Example_Where_Clause" />
    </if>
    <if test="orderByClause != null">
      order by ${orderByClause}
    </if>
  </select>
  <select id="selectByPrimaryKey" parameterType="java.lang.Integer" resultMap="BaseResultMap">
    <!--
      WARNING - @mbg.generated
      This element is automatically generated by MyBatis Generator, do not modify.
      This element was generated on Tue May 14 10:48:08 CST 2019.
    -->
    select 
    <include refid="Base_Column_List" />
    from shopcategory
    where shopCategoryId = #{shopcategoryid,jdbcType=INTEGER}
  </select>
  <delete id="deleteByPrimaryKey" parameterType="java.lang.Integer">
    <!--
      WARNING - @mbg.generated
      This element is automatically generated by MyBatis Generator, do not modify.
      This element was generated on Tue May 14 10:48:08 CST 2019.
    -->
    delete from shopcategory
    where shopCategoryId = #{shopcategoryid,jdbcType=INTEGER}
  </delete>
  <delete id="deleteByExample" parameterType="club.bagedate.o2o.entity.ShopCategoryExample">
    <!--
      WARNING - @mbg.generated
      This element is automatically generated by MyBatis Generator, do not modify.
      This element was generated on Tue May 14 10:48:08 CST 2019.
    -->
    delete from shopcategory
    <if test="_parameter != null">
      <include refid="Example_Where_Clause" />
    </if>
  </delete>
  <insert id="insert" parameterType="club.bagedate.o2o.entity.ShopCategory">
    <!--
      WARNING - @mbg.generated
      This element is automatically generated by MyBatis Generator, do not modify.
      This element was generated on Tue May 14 10:48:08 CST 2019.
    -->
    insert into shopcategory (shopCategoryId, shopCategoryPriority, 
      shopCategoryParentId, shopCategoryName, 
      shopCategoryDesc, shopCategoryImg, shopCategoryCreateTime, 
      shopCategoryUpdateTime)
    values (#{shopcategoryid,jdbcType=INTEGER}, #{shopcategorypriority,jdbcType=INTEGER}, 
      #{shopcategoryparentid,jdbcType=INTEGER}, #{shopcategoryname,jdbcType=VARCHAR}, 
      #{shopcategorydesc,jdbcType=VARCHAR}, #{shopcategoryimg,jdbcType=VARCHAR}, #{shopcategorycreatetime,jdbcType=TIMESTAMP}, 
      #{shopcategoryupdatetime,jdbcType=TIMESTAMP})
  </insert>
  <insert id="insertSelective" parameterType="club.bagedate.o2o.entity.ShopCategory">
    <!--
      WARNING - @mbg.generated
      This element is automatically generated by MyBatis Generator, do not modify.
      This element was generated on Tue May 14 10:48:08 CST 2019.
    -->
    insert into shopcategory
    <trim prefix="(" suffix=")" suffixOverrides=",">
      <if test="shopcategoryid != null">
        shopCategoryId,
      </if>
      <if test="shopcategorypriority != null">
        shopCategoryPriority,
      </if>
      <if test="shopcategoryparentid != null">
        shopCategoryParentId,
      </if>
      <if test="shopcategoryname != null">
        shopCategoryName,
      </if>
      <if test="shopcategorydesc != null">
        shopCategoryDesc,
      </if>
      <if test="shopcategoryimg != null">
        shopCategoryImg,
      </if>
      <if test="shopcategorycreatetime != null">
        shopCategoryCreateTime,
      </if>
      <if test="shopcategoryupdatetime != null">
        shopCategoryUpdateTime,
      </if>
    </trim>
    <trim prefix="values (" suffix=")" suffixOverrides=",">
      <if test="shopcategoryid != null">
        #{shopcategoryid,jdbcType=INTEGER},
      </if>
      <if test="shopcategorypriority != null">
        #{shopcategorypriority,jdbcType=INTEGER},
      </if>
      <if test="shopcategoryparentid != null">
        #{shopcategoryparentid,jdbcType=INTEGER},
      </if>
      <if test="shopcategoryname != null">
        #{shopcategoryname,jdbcType=VARCHAR},
      </if>
      <if test="shopcategorydesc != null">
        #{shopcategorydesc,jdbcType=VARCHAR},
      </if>
      <if test="shopcategoryimg != null">
        #{shopcategoryimg,jdbcType=VARCHAR},
      </if>
      <if test="shopcategorycreatetime != null">
        #{shopcategorycreatetime,jdbcType=TIMESTAMP},
      </if>
      <if test="shopcategoryupdatetime != null">
        #{shopcategoryupdatetime,jdbcType=TIMESTAMP},
      </if>
    </trim>
  </insert>
  <select id="countByExample" parameterType="club.bagedate.o2o.entity.ShopCategoryExample" resultType="java.lang.Long">
    <!--
      WARNING - @mbg.generated
      This element is automatically generated by MyBatis Generator, do not modify.
      This element was generated on Tue May 14 10:48:08 CST 2019.
    -->
    select count(*) from shopcategory
    <if test="_parameter != null">
      <include refid="Example_Where_Clause" />
    </if>
  </select>
  <update id="updateByExampleSelective" parameterType="map">
    <!--
      WARNING - @mbg.generated
      This element is automatically generated by MyBatis Generator, do not modify.
      This element was generated on Tue May 14 10:48:08 CST 2019.
    -->
    update shopcategory
    <set>
      <if test="record.shopcategoryid != null">
        shopCategoryId = #{record.shopcategoryid,jdbcType=INTEGER},
      </if>
      <if test="record.shopcategorypriority != null">
        shopCategoryPriority = #{record.shopcategorypriority,jdbcType=INTEGER},
      </if>
      <if test="record.shopcategoryparentid != null">
        shopCategoryParentId = #{record.shopcategoryparentid,jdbcType=INTEGER},
      </if>
      <if test="record.shopcategoryname != null">
        shopCategoryName = #{record.shopcategoryname,jdbcType=VARCHAR},
      </if>
      <if test="record.shopcategorydesc != null">
        shopCategoryDesc = #{record.shopcategorydesc,jdbcType=VARCHAR},
      </if>
      <if test="record.shopcategoryimg != null">
        shopCategoryImg = #{record.shopcategoryimg,jdbcType=VARCHAR},
      </if>
      <if test="record.shopcategorycreatetime != null">
        shopCategoryCreateTime = #{record.shopcategorycreatetime,jdbcType=TIMESTAMP},
      </if>
      <if test="record.shopcategoryupdatetime != null">
        shopCategoryUpdateTime = #{record.shopcategoryupdatetime,jdbcType=TIMESTAMP},
      </if>
    </set>
    <if test="_parameter != null">
      <include refid="Update_By_Example_Where_Clause" />
    </if>
  </update>
  <update id="updateByExample" parameterType="map">
    <!--
      WARNING - @mbg.generated
      This element is automatically generated by MyBatis Generator, do not modify.
      This element was generated on Tue May 14 10:48:08 CST 2019.
    -->
    update shopcategory
    set shopCategoryId = #{record.shopcategoryid,jdbcType=INTEGER},
      shopCategoryPriority = #{record.shopcategorypriority,jdbcType=INTEGER},
      shopCategoryParentId = #{record.shopcategoryparentid,jdbcType=INTEGER},
      shopCategoryName = #{record.shopcategoryname,jdbcType=VARCHAR},
      shopCategoryDesc = #{record.shopcategorydesc,jdbcType=VARCHAR},
      shopCategoryImg = #{record.shopcategoryimg,jdbcType=VARCHAR},
      shopCategoryCreateTime = #{record.shopcategorycreatetime,jdbcType=TIMESTAMP},
      shopCategoryUpdateTime = #{record.shopcategoryupdatetime,jdbcType=TIMESTAMP}
    <if test="_parameter != null">
      <include refid="Update_By_Example_Where_Clause" />
    </if>
  </update>
  <update id="updateByPrimaryKeySelective" parameterType="club.bagedate.o2o.entity.ShopCategory">
    <!--
      WARNING - @mbg.generated
      This element is automatically generated by MyBatis Generator, do not modify.
      This element was generated on Tue May 14 10:48:08 CST 2019.
    -->
    update shopcategory
    <set>
      <if test="shopcategorypriority != null">
        shopCategoryPriority = #{shopcategorypriority,jdbcType=INTEGER},
      </if>
      <if test="shopcategoryparentid != null">
        shopCategoryParentId = #{shopcategoryparentid,jdbcType=INTEGER},
      </if>
      <if test="shopcategoryname != null">
        shopCategoryName = #{shopcategoryname,jdbcType=VARCHAR},
      </if>
      <if test="shopcategorydesc != null">
        shopCategoryDesc = #{shopcategorydesc,jdbcType=VARCHAR},
      </if>
      <if test="shopcategoryimg != null">
        shopCategoryImg = #{shopcategoryimg,jdbcType=VARCHAR},
      </if>
      <if test="shopcategorycreatetime != null">
        shopCategoryCreateTime = #{shopcategorycreatetime,jdbcType=TIMESTAMP},
      </if>
      <if test="shopcategoryupdatetime != null">
        shopCategoryUpdateTime = #{shopcategoryupdatetime,jdbcType=TIMESTAMP},
      </if>
    </set>
    where shopCategoryId = #{shopcategoryid,jdbcType=INTEGER}
  </update>
  <update id="updateByPrimaryKey" parameterType="club.bagedate.o2o.entity.ShopCategory">
    <!--
      WARNING - @mbg.generated
      This element is automatically generated by MyBatis Generator, do not modify.
      This element was generated on Tue May 14 10:48:08 CST 2019.
    -->
    update shopcategory
    set shopCategoryPriority = #{shopcategorypriority,jdbcType=INTEGER},
      shopCategoryParentId = #{shopcategoryparentid,jdbcType=INTEGER},
      shopCategoryName = #{shopcategoryname,jdbcType=VARCHAR},
      shopCategoryDesc = #{shopcategorydesc,jdbcType=VARCHAR},
      shopCategoryImg = #{shopcategoryimg,jdbcType=VARCHAR},
      shopCategoryCreateTime = #{shopcategorycreatetime,jdbcType=TIMESTAMP},
      shopCategoryUpdateTime = #{shopcategoryupdatetime,jdbcType=TIMESTAMP}
    where shopCategoryId = #{shopcategoryid,jdbcType=INTEGER}
  </update>
</mapper>